lyric_component_ts_transpiling/__init__.py
lyric_component_ts_transpiling/component_ts_transpiling.wasm
lyric_component_ts_transpiling-0.1.7.dist-info/METADATA
lyric_component_ts_transpiling-0.1.7.dist-info/WHEEL
lyric_component_ts_transpiling-0.1.7.dist-info/RECORD
