Metadata-Version: 2.3
Name: lyric-component-ts-transpiling
Version: 0.1.7
Summary: Add your description here
Author-email: Fangyin Cheng <staneyffer@gmail.com>
Requires-Python: >=3.10
Requires-Dist: lyric-task
